{
    "documentAuthors": [
        "Ilse Ham"
    ],
    "uuid": null,
    "authors": [
        {
            "fullName": "Ilse Ham",
            "referenceName": null,
            "reference": {
                "value": "111613"
            },
            "firstName": "Ilse",
            "infix": null,
            "lastName": "Ham",
            "emailAddress": "i.ham2@hotmail.com",
            "type": "author"
        }
    ],
    "documentDate": "2021-06-24T12:53:07Z",
    "bulkId": "bulk-17041658-refresh_all",
    "identifier": 171121,
    "title": "Nederlands havo 2",
    "description": "",
    "lastModifiedDate": "2021-06-24T12:53:07+02:00",
    "dateCreated": "2020-12-14T16:33:02+01:00",
    "published": true,
    "publisher": null,
    "team": {
        "reference": {
            "value": "wikiwijs_maken_authors"
        },
        "name": "Wikiwijs Maken Auteurs",
        "members": [
            {
                "fullName": null,
                "referenceName": "Ham, Ilse",
                "reference": {
                    "value": "111613"
                },
                "firstName": "Ilse",
                "infix": null,
                "lastName": "Ham",
                "emailAddress": "i.ham2@hotmail.com",
                "type": "author"
            }
        ],
        "emailAddress": null,
        "description": null
    },
    "metadata": {
        "license": {
            "identifier": "cc-by-40",
            "name": "CC Naamsvermelding 4.0 Internationale licentie",
            "description": "De Internationale Creative Commons 4.0 licentie waarbij de gebruiker het werk mag kopi\u00ebren, verspreiden en doorgeven en afgeleide werken mag maken onder de voorwaarde: Naamsvermelding, zie http://creativecommons.org/licenses/by/4.0/.",
            "link": "http://creativecommons.org/licenses/by/4.0/"
        },
        "webAddress": "https://maken.wikiwijs.nl/171121/"
    },
    "sections": [
        {
            "reference": {
                "value": "6469529"
            },
            "heading": {
                "type": "heading",
                "content": "Welkom",
                "level": 1
            },
            "items": [
                {
                    "type": "paragraph",
                    "content": "<p>Van harte welkom op deze site voor de lessen Nederlands. Ik hoop dat je met deze site steeds een stapje verder komt en steeds wat beter wordt in het vak Nederlands! Veel plezier met oefenen!</p>\n<p>Onder het kopje 'Hoe werkt deze site?' kun je meer informatie vinden over deze site.</p>\n<p> </p>\n<p> </p>\n"
                },
                {
                    "type": "image",
                    "src": "https://maken.wikiwijs.nl/userfiles/5/58d2bfc92aa07b428f1f55b82292cfec507d893e.jpg",
                    "altText": "",
                    "alignment": "right",
                    "scale": 0.25,
                    "link": ""
                }
            ],
            "sections": []
        },
        {
            "reference": {
                "value": "6469530"
            },
            "heading": {
                "type": "heading",
                "content": "Hoe werkt deze site?",
                "level": 1
            },
            "items": [
                {
                    "type": "paragraph",
                    "content": "<p>Het is een gekke tijd! De komende tijd moeten we helaas even thuisblijven. Geen zorgen! Met deze site kun je namelijk thuis de uitleg alsnog bekijken.</p>\n<p> </p>\n<p>Wat moet je doen?</p>\n<p>1. Klik het onderwerp aan waar de docent mee bezig is. Als je dit niet weet, stuur de docent dan een mailtje of een bericht via SomToday. Zorg ervoor dat je SomToday ook goed controleert, want waarschijnlijk staat daar ook aangegeven wat je moet doen.</p>\n<p>2. Je kunt nu per onderwerp kennisclips bekijken met uitleg. De leerdoelen worden per hoofdstuk besproken. Ook worden er in de kennisclip oefeningen uit het boek genoemd die bij de lesstof aansluiten. Tot slot staat er bij elk hoofdstuk een kopje met extra materiaal. Hieronder kun je bijvoorbeeld belangrijke leerstof of oefentoetsen vinden.</p>\n<p>3. Heb je vragen? Mail dan even naar iham02@leniz.nl of stuur een berichtje via SomToday!</p>\n"
                }
            ],
            "sections": []
        },
        {
            "reference": {
                "value": "6469533"
            },
            "heading": {
                "type": "heading",
                "content": "Woordenschat",
                "level": 1
            },
            "items": [],
            "sections": [
                {
                    "reference": {
                        "value": "6469559"
                    },
                    "heading": {
                        "type": "heading",
                        "content": "Woordenschat",
                        "level": 2
                    },
                    "items": [
                        {
                            "type": "paragraph",
                            "content": "<p>Bij dit onderdeel kun je uitleg over woordenschat vinden.</p>\n<p> </p>\n<p> </p>\n<p> </p>\n"
                        },
                        {
                            "type": "image",
                            "src": "https://maken.wikiwijs.nl/userfiles/7/7088d57436bdcbac0fddba4bbc85cc916bd5a138.jpg",
                            "altText": "",
                            "alignment": "right",
                            "scale": 0.2,
                            "link": ""
                        }
                    ],
                    "sections": []
                },
                {
                    "reference": {
                        "value": "6469547"
                    },
                    "heading": {
                        "type": "heading",
                        "content": "Woordenschat hoofdstuk 1: vergelijking",
                        "level": 2
                    },
                    "items": [
                        {
                            "type": "paragraph",
                            "content": "<p>Het onderwerp van hoofdstuk 1 is de vergelijking. Het leerdoel van dit hoofdstuk is:</p>\n<p>1. Aan het einde van deze les kun je vergelijkingen herkennen en begrijpen.</p>\n<p> </p>\n<p>In de kennisclip kun je uitleg vinden over vergelijkingen. Bij de extra materialen kun je de leerstof voor dit hoofdstuk vinden. Het is van belang dat je de betekenissen van de vergelijkingen en van de woorden uit dit hoofdstuk weet. Ook is het belangrijk dat je het verschil tussen het beeld (b) en het object (o) weet.</p>\n<p> </p>\n"
                        },
                        {
                            "type": "video",
                            "url": "https://youtu.be/A4Ugyx-v6dE",
                            "align": "left",
                            "caption": "Vergelijking",
                            "poster": "https://img.youtube.com/vi/A4Ugyx-v6dE/maxresdefault.jpg"
                        }
                    ],
                    "sections": []
                },
                {
                    "reference": {
                        "value": "6469549"
                    },
                    "heading": {
                        "type": "heading",
                        "content": "Woordenschat hoofdstuk 2: metaforen en personificaties",
                        "level": 2
                    },
                    "items": [
                        {
                            "type": "paragraph",
                            "content": "<p>Het onderwerp van hoofdstuk 2 is metaforen en personificaties. Het leerdoel van dit hoofdstuk is:</p>\n<p>1. Aan het einde van deze les kun je metaforen en personificaties herkennen en begrijpen.</p>\n<p> </p>\n<p>In de kennisclip kun je uitleg vinden over metaforen en personificaties. Bij de extra materialen kun je de leerstof voor dit hoofdstuk vinden. Het is van belang dat je de betekenissen van de metaforen, personificaties en van de woorden uit dit hoofdstuk weet.</p>\n<p> </p>\n"
                        },
                        {
                            "type": "video",
                            "url": "https://youtu.be/j8Wfoj28bxc",
                            "align": "left",
                            "caption": "Metaforen en personificaties",
                            "poster": "https://img.youtube.com/vi/j8Wfoj28bxc/maxresdefault.jpg"
                        }
                    ],
                    "sections": []
                },
                {
                    "reference": {
                        "value": "6469550"
                    },
                    "heading": {
                        "type": "heading",
                        "content": "Woordenschat hoofdstuk 3: voorzetsels en voorzetseluitdrukkingen",
                        "level": 2
                    },
                    "items": [
                        {
                            "type": "paragraph",
                            "content": "<p>Het onderwerp van hoofdstuk 3 is voorzetsels en voorzetseluitdrukkingen. Het leerdoel van dit hoofdstuk is:</p>\n<p>1. Aan het einde van deze les kun je vaste voorzetsels en voorzetseluitdrukkingen herkennen, begrijpen en gebruiken.</p>\n<p> </p>\n<p>In de kennisclip kun je uitleg vinden over vaste voorzetsels en voorzetseluitdrukkingen. Bij de extra materialen kun je de leerstof voor dit hoofdstuk vinden. Het is van belang dat je de betekenissen van de uitdrukkingen en de woorden uit dit hoofdstuk weet.</p>\n<p> </p>\n"
                        },
                        {
                            "type": "video",
                            "url": "https://youtu.be/EwSQSyocsj8",
                            "align": "left",
                            "caption": "Voorzetsels en voorzetseluitdrukkingen",
                            "poster": "https://img.youtube.com/vi/EwSQSyocsj8/maxresdefault.jpg"
                        }
                    ],
                    "sections": []
                },
                {
                    "reference": {
                        "value": "6612912"
                    },
                    "heading": {
                        "type": "heading",
                        "content": "Woordenschat hoofdstuk 4: rijmende uitdrukkingen",
                        "level": 2
                    },
                    "items": [
                        {
                            "type": "paragraph",
                            "content": "<p>Het onderwerp van hoofdstuk 4 is rijmende uitdrukkingen. Het leerdoel van dit hoofdstuk is:</p>\n<p>1. Aan het einde van deze les kun je rijmende uitdrukkingen herkennen en begrijpen.</p>\n<p> </p>\n<p>In de kennisclip kun je uitleg vinden over rijmende uitdrukkingen. Bij de extra materialen kun je de leerstof voor dit hoofdstuk vinden. Het is van belang dat je de betekenissen van de uitdrukkingen en de woorden uit dit hoofdstuk weet.</p>\n<p> </p>\n"
                        },
                        {
                            "type": "video",
                            "url": "https://youtu.be/hKADF2esGQw",
                            "align": "left",
                            "caption": "Rijmende uitdrukkingen",
                            "poster": "https://img.youtube.com/vi/hKADF2esGQw/maxresdefault.jpg"
                        }
                    ],
                    "sections": []
                },
                {
                    "reference": {
                        "value": "6612914"
                    },
                    "heading": {
                        "type": "heading",
                        "content": "Woordenschat hoofdstuk 5: uitdrukkingen uit handel en scheepvaart",
                        "level": 2
                    },
                    "items": [
                        {
                            "type": "paragraph",
                            "content": "<p>Het onderwerp van hoofdstuk 5 is uitdrukkingen uit handel en scheepvaart. Het leerdoel van dit hoofdstuk is:</p>\n<p>1. Aan het einde van deze les kun je uitdrukkingen uit handel en scheepvaart herkennen en begrijpen.</p>\n<p> </p>\n<p>In de kennisclip kun je uitleg vinden over uitdrukkingen uit handel en scheepvaart. Bij de extra materialen kun je over een tijdje de leerstof voor dit hoofdstuk vinden. Het is van belang dat je de betekenissen van de uitdrukkingen en de woorden uit dit hoofdstuk weet.</p>\n<p> </p>\n"
                        },
                        {
                            "type": "video",
                            "url": "https://youtu.be/t1NDW_sv4Ps",
                            "align": "left",
                            "caption": "Uitdrukkingen uit de tijd van handel en scheepvaart",
                            "poster": "https://img.youtube.com/vi/t1NDW_sv4Ps/maxresdefault.jpg"
                        }
                    ],
                    "sections": []
                },
                {
                    "reference": {
                        "value": "6612915"
                    },
                    "heading": {
                        "type": "heading",
                        "content": "Woordenschat hoofdstuk 6: oude naamvallen",
                        "level": 2
                    },
                    "items": [
                        {
                            "type": "paragraph",
                            "content": "<p>Het onderwerp van hoofdstuk 6 is oude naamvallen. Het leerdoel van dit hoofdstuk is:</p>\n<p>1. Aan het einde van deze les kun je oude naamvallen herkennen en begrijpen.</p>\n<p> </p>\n<p>In de kennisclip kun je uitleg vinden over oude naamvallen. Bij de extra materialen kun je over een tijdje de leerstof voor dit hoofdstuk vinden. Het is van belang dat je de betekenissen van de uitdrukkingen en de woorden uit dit hoofdstuk weet.</p>\n<p> </p>\n"
                        },
                        {
                            "type": "video",
                            "url": "https://youtu.be/PR2lU02_WqM",
                            "align": "left",
                            "caption": "Oude naamvallen",
                            "poster": "https://img.youtube.com/vi/PR2lU02_WqM/maxresdefault.jpg"
                        }
                    ],
                    "sections": []
                },
                {
                    "reference": {
                        "value": "6469564"
                    },
                    "heading": {
                        "type": "heading",
                        "content": "Woordenschat extra materiaal ",
                        "level": 2
                    },
                    "items": [
                        {
                            "type": "file",
                            "title": "Woordenschat hoofdstuk 1: leerstof",
                            "file": "https://maken.wikiwijs.nl/userfiles/5/58818c9900178f9fd83aabb2c5201f0c1d5203c7.docx"
                        },
                        {
                            "type": "file",
                            "title": "Woordenschat hoofdstuk 2: leerstof",
                            "file": "https://maken.wikiwijs.nl/userfiles/d/d71961c3fb7da1f3352c2831c94471b2fd89705e.docx"
                        },
                        {
                            "type": "file",
                            "title": "Woordenschat hoofdstuk 3: leerstof",
                            "file": "https://maken.wikiwijs.nl/userfiles/a/afc34975b00908f060c88065c5dfd9081acd5f92.docx"
                        },
                        {
                            "type": "file",
                            "title": "Woordenschat hoofdstuk 4: leerstof",
                            "file": "https://maken.wikiwijs.nl/userfiles/7/7d4a223235c66fe6d199f9f8045eb2e11b7dcbfd.docx"
                        },
                        {
                            "type": "file",
                            "title": "Woordenschat hoofdstuk 5: leerstof",
                            "file": "https://maken.wikiwijs.nl/userfiles/1/1de5cd0e3e9e7679b1ae345c6a5a7f6af2aa2410.docx"
                        },
                        {
                            "type": "file",
                            "title": "Woordenschat hoofdstuk 6: leerstof",
                            "file": "https://maken.wikiwijs.nl/userfiles/1/1acdd9d2a588f823a6a883b582d190d81f50c534.docx"
                        }
                    ],
                    "sections": []
                }
            ]
        },
        {
            "reference": {
                "value": "6469601"
            },
            "heading": {
                "type": "heading",
                "content": "Leesvaardigheid",
                "level": 1
            },
            "items": [],
            "sections": [
                {
                    "reference": {
                        "value": "6469593"
                    },
                    "heading": {
                        "type": "heading",
                        "content": "Leesvaardigheid",
                        "level": 2
                    },
                    "items": [
                        {
                            "type": "paragraph",
                            "content": "<p>Bij dit onderdeel kun je uitleg over leesvaardigheid vinden.</p>\n<p> </p>\n<p> </p>\n"
                        },
                        {
                            "type": "image",
                            "src": "https://maken.wikiwijs.nl/userfiles/e/efca11cc158400ba0d17469a32a2d3e2bdc8292b.png",
                            "altText": "",
                            "alignment": "right",
                            "scale": 0.25,
                            "link": ""
                        }
                    ],
                    "sections": []
                },
                {
                    "reference": {
                        "value": "6469570"
                    },
                    "heading": {
                        "type": "heading",
                        "content": "Leesvaardigheid hoofdstuk 1",
                        "level": 2
                    },
                    "items": [
                        {
                            "type": "paragraph",
                            "content": "<p>Het onderwerp van hoofdstuk 1 is hoofd- en bijzaken en kernzinnen. De leerdoelen van dit hoofdstuk zijn:</p>\n<p>1. Aan het einde van deze les kun je onderscheid maken tussen hoofd- en bijzaken;</p>\n<p>2. Aan het einde van deze les kun je kernzinnen herkennen;</p>\n<p>3. Aan het einde van deze les kun je een korte samenvatting maken.</p>\n<p> </p>\n<p>In de kennisclip kun je uitleg vinden over hoofdzaken, bijzaken en kernzinnen. Bij de extra materialen kun je de leerstof voor dit hoofdstuk vinden. Het is van belang dat je de de theorie goed weet, maar dat je dit ook kunt toepassen in teksten.</p>\n<p> </p>\n"
                        },
                        {
                            "type": "video",
                            "url": "https://youtu.be/6enczpP1Hao",
                            "align": "left",
                            "caption": "Hoofdzaken, bijzaken en kernzinnen",
                            "poster": "https://img.youtube.com/vi/6enczpP1Hao/maxresdefault.jpg"
                        }
                    ],
                    "sections": []
                },
                {
                    "reference": {
                        "value": "6469571"
                    },
                    "heading": {
                        "type": "heading",
                        "content": "Leesvaardigheid hoofdstuk 2",
                        "level": 2
                    },
                    "items": [
                        {
                            "type": "paragraph",
                            "content": "<p>Het onderwerp van hoofdstuk 2 is tekstverbanden en signaalwoorden. De leerdoelen van dit hoofdstuk zijn:</p>\n<p>1. Aan het einde van deze les kun je tekstverbanden herkennen aan de hand van signaalwoorden;</p>\n<p>2. Aan het einde van deze les kun je concluderende, redengevende en oorzakelijke verbanden in de tekst herkennen.</p>\n<p> </p>\n<p>In de kennisclip kun je uitleg vinden over tekstverbanden en signaalwoorden. Bij de extra materialen kun je de leerstof voor dit hoofdstuk vinden. Het is van belang dat je de de theorie goed weet, maar dat je dit ook kunt toepassen in teksten.</p>\n<p> </p>\n"
                        },
                        {
                            "type": "video",
                            "url": "https://youtu.be/0nzddaUYIsc",
                            "align": "left",
                            "caption": "Tekstverbanden en signaalwoorden",
                            "poster": "https://img.youtube.com/vi/0nzddaUYIsc/maxresdefault.jpg"
                        }
                    ],
                    "sections": []
                },
                {
                    "reference": {
                        "value": "6666748"
                    },
                    "heading": {
                        "type": "heading",
                        "content": "Leesvaardigheid hoofdstuk 3",
                        "level": 2
                    },
                    "items": [
                        {
                            "type": "paragraph",
                            "content": "<p>Het onderwerp van hoofdstuk 3 is tekstverbanden en signaalwoorden. De leerdoelen van dit hoofdstuk zijn:</p>\n<p>1. Aan het einde van deze les kun je tekstverbanden herkennen aan de hand van signaalwoorden;</p>\n<p>2. Aan het einde van deze les kun je een vergelijkend en samenvattend verband en doel-middelverband in de tekst herkennen.</p>\n<p> </p>\n<p>In de kennisclip kun je uitleg vinden over tekstverbanden en signaalwoorden.</p>\n<p> </p>\n"
                        },
                        {
                            "type": "video",
                            "url": "https://youtu.be/YD_tCMGAImk",
                            "align": "left",
                            "caption": "Tekstverbanden en signaalwoorden",
                            "poster": "https://img.youtube.com/vi/YD_tCMGAImk/maxresdefault.jpg"
                        }
                    ],
                    "sections": []
                },
                {
                    "reference": {
                        "value": "6666749"
                    },
                    "heading": {
                        "type": "heading",
                        "content": "Leesvaardigheid hoofdstuk 4",
                        "level": 2
                    },
                    "items": [
                        {
                            "type": "paragraph",
                            "content": "<p>Het onderwerp van hoofdstuk 4 is feiten, meningen en argumenten. De leerdoelen van dit hoofdstuk zijn:</p>\n<p>1. Aan het einde van deze les kun je onderscheid maken tussen standpunten en argumenten;</p>\n<p>2. Aan het einde van deze les kun je tekstverbanden herkennen aan de hand van signaalwoorden.</p>\n<p> </p>\n<p>In de kennisclip kun je uitleg vinden over feiten, meningen en argumenten.</p>\n<p> </p>\n"
                        },
                        {
                            "type": "video",
                            "url": "https://youtu.be/AEaSqcPuioA",
                            "align": "left",
                            "caption": "Feiten, meningen en argumenten",
                            "poster": "https://img.youtube.com/vi/AEaSqcPuioA/maxresdefault.jpg"
                        }
                    ],
                    "sections": []
                },
                {
                    "reference": {
                        "value": "6666750"
                    },
                    "heading": {
                        "type": "heading",
                        "content": "Leesvaardigheid hoofdstuk 5",
                        "level": 2
                    },
                    "items": [
                        {
                            "type": "paragraph",
                            "content": "<p>Het onderwerp van hoofdstuk 5 is kritisch lezen. Het leerdoel van dit hoofdstuk is:</p>\n<p>1. Aan het einde van deze les kun je kritisch beoordelen of een tekst objectief en betrouwbaar is.</p>\n<p> </p>\n<p>In de kennisclip kun je uitleg vinden over kritisch lezen. </p>\n<p> </p>\n"
                        },
                        {
                            "type": "video",
                            "url": "https://youtu.be/41DHQFGuMBk",
                            "align": "left",
                            "caption": "Kritisch lezen",
                            "poster": "https://img.youtube.com/vi/41DHQFGuMBk/maxresdefault.jpg"
                        }
                    ],
                    "sections": []
                },
                {
                    "reference": {
                        "value": "6666751"
                    },
                    "heading": {
                        "type": "heading",
                        "content": "Leesvaardigheid hoofdstuk 6",
                        "level": 2
                    },
                    "items": [
                        {
                            "type": "paragraph",
                            "content": "<p>Het onderwerp van hoofdstuk 6 is tekst en publiek. Het leerdoel van dit hoofdstuk is:</p>\n<p>1. Aan het einde van deze les kun je bepalen voor welk publiek een tekst geschreven is.</p>\n<p> </p>\n<p>In de kennisclip kun je uitleg vinden over tekst en publiek.</p>\n<p> </p>\n"
                        },
                        {
                            "type": "video",
                            "url": "https://youtu.be/a_LlmlUO14o",
                            "align": "left",
                            "caption": "Tekst en publiek",
                            "poster": "https://img.youtube.com/vi/a_LlmlUO14o/maxresdefault.jpg"
                        }
                    ],
                    "sections": []
                },
                {
                    "reference": {
                        "value": "6469584"
                    },
                    "heading": {
                        "type": "heading",
                        "content": "Leesvaardigheid extra materiaal",
                        "level": 2
                    },
                    "items": [
                        {
                            "type": "file",
                            "title": "Leesvaardigheid hoofdstuk 1 en 2: leerstof",
                            "file": "https://maken.wikiwijs.nl/userfiles/6/65b4d8f635abfae3de114982d771f1b1379b3ba2.docx"
                        }
                    ],
                    "sections": []
                }
            ]
        },
        {
            "reference": {
                "value": "6469534"
            },
            "heading": {
                "type": "heading",
                "content": "Grammatica",
                "level": 1
            },
            "items": [],
            "sections": [
                {
                    "reference": {
                        "value": "6469604"
                    },
                    "heading": {
                        "type": "heading",
                        "content": "Grammatica hoofdstuk 1 t/m 3",
                        "level": 2
                    },
                    "items": [
                        {
                            "type": "paragraph",
                            "content": "<p>Bij dit onderdeel kun je uitleg over grammatica vinden.</p>\n<p> </p>\n<p> </p>\n"
                        },
                        {
                            "type": "image",
                            "src": "https://maken.wikiwijs.nl/userfiles/4/4a1082c6844f0fe4743a14758fdf50f47510c5ac.png",
                            "altText": "",
                            "alignment": "right",
                            "scale": 0.35,
                            "link": ""
                        }
                    ],
                    "sections": []
                },
                {
                    "reference": {
                        "value": "6469662"
                    },
                    "heading": {
                        "type": "heading",
                        "content": "Grammatica herhaling zinsdelen havo 1",
                        "level": 2
                    },
                    "items": [
                        {
                            "type": "paragraph",
                            "content": "<p>Je kunt hier uitleg vinden over de stof van havo 1. De volgende onderwerpen worden behandeld:</p>\n<p>- Hoe maak ik zinsdelen en hoe vind ik de persoonsvorm?</p>\n<p>- Hoe vind ik het onderwerp?</p>\n<p>- Hoe vind ik het werkwoordelijk gezegde?</p>\n<p>- Hoe vind ik het lijdend en meewerkend voorwerp?</p>\n<p>- Hoe vind ik de bijwoordelijke bepaling?</p>\n<p> </p>\n<p> </p>\n"
                        },
                        {
                            "type": "paragraph",
                            "content": "<p> </p>\n<p><strong>ZINSDELEN EN PERSOONSVORM</strong></p>\n"
                        },
                        {
                            "type": "video",
                            "url": "https://youtu.be/5V0vv2W5R00",
                            "align": "left",
                            "caption": "Zinsdelen en persoonsvorm",
                            "poster": "https://img.youtube.com/vi/5V0vv2W5R00/maxresdefault.jpg"
                        },
                        {
                            "type": "paragraph",
                            "content": "<p> </p>\n<p> </p>\n<p><strong>ONDERWERP</strong></p>\n"
                        },
                        {
                            "type": "video",
                            "url": "https://youtu.be/lk7yb-2Ytp4",
                            "align": "left",
                            "caption": "Onderwerp",
                            "poster": "https://img.youtube.com/vi/lk7yb-2Ytp4/maxresdefault.jpg"
                        },
                        {
                            "type": "paragraph",
                            "content": "<p> </p>\n<p> </p>\n<p><strong>WERKWOORDELIJK GEZEGDE</strong></p>\n"
                        },
                        {
                            "type": "video",
                            "url": "https://youtu.be/_nAw2K__DlU",
                            "align": "left",
                            "caption": "Werkwoordelijk gezegde",
                            "poster": "https://img.youtube.com/vi/_nAw2K__DlU/maxresdefault.jpg"
                        },
                        {
                            "type": "paragraph",
                            "content": "<p> </p>\n<p> </p>\n<p><strong>LIJDEND EN MEEWERKEND VOORWERP</strong></p>\n"
                        },
                        {
                            "type": "video",
                            "url": "https://youtu.be/JVB1seykzw0",
                            "align": "left",
                            "caption": "Lijdend en meewerkend voorwerp",
                            "poster": "https://img.youtube.com/vi/JVB1seykzw0/maxresdefault.jpg"
                        },
                        {
                            "type": "paragraph",
                            "content": "<p> </p>\n<p> </p>\n<p><strong>BIJWOORDELIJKE BEPALING</strong></p>\n"
                        },
                        {
                            "type": "video",
                            "url": "https://youtu.be/c8Z2HHJVkk0",
                            "align": "left",
                            "caption": "Bijwoordelijke bepaling",
                            "poster": "https://img.youtube.com/vi/c8Z2HHJVkk0/maxresdefault.jpg"
                        }
                    ],
                    "sections": []
                },
                {
                    "reference": {
                        "value": "6469663"
                    },
                    "heading": {
                        "type": "heading",
                        "content": "Grammatica herhaling woordsoorten havo 1",
                        "level": 2
                    },
                    "items": [
                        {
                            "type": "paragraph",
                            "content": "<p>Je kunt hier uitleg vinden over de stof van havo 1. De volgende onderwerpen worden behandeld:</p>\n<p>- Wat zijn woordsoorten, zelfstandig naamwoorden en lidwoorden?</p>\n<p>- Wat is een bijvoeglijk naamwoord?</p>\n<p>- Wat zijn zelfstandig werkwoorden en hulpwerkwoorden?</p>\n<p>- Wat zijn aanwijzend en vragend voornaamwoorden?</p>\n<p>- Wat zijn voorzetsels?</p>\n<p>- Wat zijn bijwoorden?</p>\n"
                        },
                        {
                            "type": "paragraph",
                            "content": "<p> </p>\n<p> </p>\n<p><strong>ZELFSTANDIG NAAMWOORD</strong></p>\n"
                        },
                        {
                            "type": "video",
                            "url": "https://youtu.be/fQ7jQzci1WM",
                            "align": "left",
                            "caption": "Zelfstandig naamwoord",
                            "poster": "https://img.youtube.com/vi/fQ7jQzci1WM/maxresdefault.jpg"
                        },
                        {
                            "type": "paragraph",
                            "content": "<p> </p>\n<p> </p>\n<p><strong>BIJVOEGLIJK NAAMWOORD</strong></p>\n"
                        },
                        {
                            "type": "video",
                            "url": "https://youtu.be/5b8HnHpXCPI",
                            "align": "left",
                            "caption": "Bijvoeglijk naamwoord",
                            "poster": "https://img.youtube.com/vi/5b8HnHpXCPI/maxresdefault.jpg"
                        },
                        {
                            "type": "paragraph",
                            "content": "<p> </p>\n<p> </p>\n<p><strong>ZELFSTANDIG WERKWOORD EN HULPWERKWOORD</strong></p>\n"
                        },
                        {
                            "type": "video",
                            "url": "https://youtu.be/5WMSBk-hnYg",
                            "align": "left",
                            "caption": "Zelfstandig werkwoord en hulpwerkwoord",
                            "poster": "https://img.youtube.com/vi/5WMSBk-hnYg/maxresdefault.jpg"
                        },
                        {
                            "type": "paragraph",
                            "content": "<p> </p>\n<p> </p>\n<p><strong>AANWIJZEND EN VRAGEND VOORNAAMWOORD</strong></p>\n"
                        },
                        {
                            "type": "video",
                            "url": "https://youtu.be/bGkQMSUm_1k",
                            "align": "left",
                            "caption": "Aanwijzend en vragend voornaamwoord",
                            "poster": "https://img.youtube.com/vi/bGkQMSUm_1k/maxresdefault.jpg"
                        },
                        {
                            "type": "paragraph",
                            "content": "<p> </p>\n<p> </p>\n<p><strong>VOORZETSEL</strong></p>\n"
                        },
                        {
                            "type": "video",
                            "url": "https://youtu.be/Wgq52LyP6nY",
                            "align": "left",
                            "caption": "Voorzetsel",
                            "poster": "https://img.youtube.com/vi/Wgq52LyP6nY/maxresdefault.jpg"
                        },
                        {
                            "type": "paragraph",
                            "content": "<p> </p>\n<p> </p>\n<p><strong>BIJWOORD</strong></p>\n"
                        },
                        {
                            "type": "video",
                            "url": "https://youtu.be/RnRfjjkuVnU",
                            "align": "left",
                            "caption": "Bijwoord",
                            "poster": "https://img.youtube.com/vi/RnRfjjkuVnU/maxresdefault.jpg"
                        }
                    ],
                    "sections": []
                },
                {
                    "reference": {
                        "value": "6469660"
                    },
                    "heading": {
                        "type": "heading",
                        "content": "Grammatica zinsdelen hoofdstuk 1",
                        "level": 2
                    },
                    "items": [
                        {
                            "type": "paragraph",
                            "content": "<p>Hoofdstuk 1 gaat over het voorzetselvoorwerp. Dit zinsdeel hoef je niet te weten voor de toets van hoofdstuk 1 t/m 3.</p>\n"
                        }
                    ],
                    "sections": []
                },
                {
                    "reference": {
                        "value": "6469661"
                    },
                    "heading": {
                        "type": "heading",
                        "content": "Grammatica woordsoorten hoofdstuk 1",
                        "level": 2
                    },
                    "items": [
                        {
                            "type": "paragraph",
                            "content": "<p>Het onderwerp van woordsoorten hoofdstuk 1 is het persoonlijk en bezittelijk voornaamwoord. Het leerdoel van dit hoofdstuk is:</p>\n<p><span class=\"font-size-14px\">1. Aan het einde van deze les kun je persoonlijke en bezittelijke voornaamwoorden herkennen.</span></p>\n<p> </p>\n<p>In de kennisclip kun je uitleg vinden over het persoonlijk en bezittlijk voornaamwoord.</p>\n"
                        },
                        {
                            "type": "video",
                            "url": "https://youtu.be/e8LR6bcG9I8",
                            "align": "left",
                            "caption": "Persoonlijk en bezittelijk voornaamwoord",
                            "poster": "https://img.youtube.com/vi/e8LR6bcG9I8/maxresdefault.jpg"
                        }
                    ],
                    "sections": []
                },
                {
                    "reference": {
                        "value": "6469664"
                    },
                    "heading": {
                        "type": "heading",
                        "content": "Grammatica zinsdelen hoofdstuk 2",
                        "level": 2
                    },
                    "items": [
                        {
                            "type": "paragraph",
                            "content": "<p>Het onderwerp van hoofdstuk 2 en 3 is het naamwoordelijk gezegde. De leerdoelen van dit hoofdstuk zijn:</p>\n<p>1. Aan het einde van deze les kun je het (werkwoordelijke en naamwoordelijke deel van het) naamwoordelijk gezegde vinden. </p>\n<p>2. Aan het einde van deze les kun je onderscheid maken tussen het werkwoordelijk en naamwoordelijk  gezegde. </p>\n<p> </p>\n<p>In de kennisclip kun je uitleg vinden over het naamwoordelijk gezegde. </p>\n"
                        },
                        {
                            "type": "video",
                            "url": "https://youtu.be/IJJy7LEWLmE",
                            "align": "left",
                            "caption": "Naamwoordelijk gezegde",
                            "poster": "https://img.youtube.com/vi/IJJy7LEWLmE/maxresdefault.jpg"
                        }
                    ],
                    "sections": []
                },
                {
                    "reference": {
                        "value": "6469666"
                    },
                    "heading": {
                        "type": "heading",
                        "content": "Grammatica woordsoorten hoofdstuk 2",
                        "level": 2
                    },
                    "items": [
                        {
                            "type": "paragraph",
                            "content": "<p>Het onderwerp van hoofdstuk 2 en 3 is het zelfstandig werkwoord, koppelwerkwoord en hulpwerkwoord. Het leerdoelen van dit hoofdstuk is:</p>\n<p>1. Aan het einde van deze les kun je zelfstandig werkwoorden, koppelwerkwoorden en hulpwerkwoorden herkennen.</p>\n<p> </p>\n<p>In de kennisclip kun je uitleg vinden over zelfstandig werkwoorden, koppelwerkwoorden en hulpwerkwoorden.</p>\n"
                        },
                        {
                            "type": "video",
                            "url": "https://youtu.be/TQXeW0eOsbA",
                            "align": "left",
                            "caption": "Zelfstandig werkwoord, koppelwerkwoord en hulpwerkwoord",
                            "poster": "https://img.youtube.com/vi/TQXeW0eOsbA/maxresdefault.jpg"
                        }
                    ],
                    "sections": []
                },
                {
                    "reference": {
                        "value": "6469665"
                    },
                    "heading": {
                        "type": "heading",
                        "content": "Grammatica zinsdelen hoofdstuk 3",
                        "level": 2
                    },
                    "items": [
                        {
                            "type": "paragraph",
                            "content": "<p>Het onderwerp van hoofdstuk 2 en 3 is het naamwoordelijk gezegde. De leerdoelen van dit hoofdstuk zijn:</p>\n<p>1. Aan het einde van deze les kun je het (werkwoordelijke en naamwoordelijke deel van het) naamwoordelijk gezegde vinden.</p>\n<p>2. Aan het einde van deze les kun je onderscheid maken tussen het werkwoordelijk en naamwoordelijk  gezegde.</p>\n<p> </p>\n<p>In de kennisclip kun je uitleg vinden over het naamwoordelijk gezegde.</p>\n<p> </p>\n"
                        },
                        {
                            "type": "video",
                            "url": "https://youtu.be/IJJy7LEWLmE",
                            "align": "left",
                            "caption": "Naamwoordelijk gezegde",
                            "poster": "https://img.youtube.com/vi/IJJy7LEWLmE/maxresdefault.jpg"
                        }
                    ],
                    "sections": []
                },
                {
                    "reference": {
                        "value": "6469667"
                    },
                    "heading": {
                        "type": "heading",
                        "content": "Grammatica woordsoorten hoofdstuk 3",
                        "level": 2
                    },
                    "items": [
                        {
                            "type": "paragraph",
                            "content": "<p>Het onderwerp van hoofdstuk 2 en 3 is het zelfstandig werkwoord, koppelwerkwoord en hulpwerkwoord. Het leerdoelen van dit hoofdstuk is:</p>\n<p>1. Aan het einde van deze les kun je zelfstandig werkwoorden, koppelwerkwoorden en hulpwerkwoorden herkennen.</p>\n<p> </p>\n<p>In de kennisclip kun je uitleg vinden over zelfstandig werkwoorden, koppelwerkwoorden en hulpwerkwoorden.</p>\n"
                        },
                        {
                            "type": "video",
                            "url": "https://youtu.be/TQXeW0eOsbA",
                            "align": "left",
                            "caption": "Zelfstandig werkwoord, koppelwerkwoord en hulpwerkwoord",
                            "poster": "https://img.youtube.com/vi/TQXeW0eOsbA/maxresdefault.jpg"
                        }
                    ],
                    "sections": []
                },
                {
                    "reference": {
                        "value": "6522381"
                    },
                    "heading": {
                        "type": "heading",
                        "content": "Grammatica zinsdelen hoofdstuk 4",
                        "level": 2
                    },
                    "items": [
                        {
                            "type": "paragraph",
                            "content": "<p>Het onderwerp van zinsdelen hoofdstuk 4 is de bijvoeglijke bepaling. Het leerdoel van dit hoofdstuk is:</p>\n<p>1. Aan het einde van deze les kun je bijvoeglijke bepalingen in een zin vinden.</p>\n<p> </p>\n<p>In de kennisclip kun je uitleg vinden over de bijvoeglijke bepaling.</p>\n<p> </p>\n"
                        },
                        {
                            "type": "video",
                            "url": "https://youtu.be/nPulrKvnuno",
                            "align": "left",
                            "caption": "Bijvoeglijke bepaling",
                            "poster": "https://img.youtube.com/vi/nPulrKvnuno/maxresdefault.jpg"
                        }
                    ],
                    "sections": []
                },
                {
                    "reference": {
                        "value": "6522382"
                    },
                    "heading": {
                        "type": "heading",
                        "content": "Grammatica woordsoorten hoofdstuk 4",
                        "level": 2
                    },
                    "items": [
                        {
                            "type": "paragraph",
                            "content": "<p>Het onderwerp van woordsoorten hoofdstuk 4 is telwoorden. Het leerdoel van dit hoofdstuk is:</p>\n<p>1. Aan het einde van deze les kun je bepaalde en onbepaalde hoofd- en rangtelwoorden in een zin vinden.</p>\n<p> </p>\n<p>In de kennisclip kun je uitleg vinden over telwoorden.</p>\n<p> </p>\n"
                        },
                        {
                            "type": "video",
                            "url": "https://youtu.be/4Ev6MDDouKg",
                            "align": "left",
                            "caption": "Telwoorden",
                            "poster": "https://img.youtube.com/vi/4Ev6MDDouKg/maxresdefault.jpg"
                        }
                    ],
                    "sections": []
                },
                {
                    "reference": {
                        "value": "6522389"
                    },
                    "heading": {
                        "type": "heading",
                        "content": "Grammatica zinsdelen hoofdstuk 5",
                        "level": 2
                    },
                    "items": [
                        {
                            "type": "paragraph",
                            "content": "<p>Het onderwerp van zinsdelen hoofdstuk 5 is enkelvoudige en samengestelde zinnen (hoofd- en bijzinnen). Het leerdoel van dit hoofdstuk is:</p>\n<p>1. Aan het einde van deze les kun je hoofd- en bijzinnen herkennen in een samengestelde zin. </p>\n<p> </p>\n<p>In de kennisclip kun je uitleg vinden over enkelvoudige en samengestelde zinnen en over hoofd- en bijzinnen.</p>\n<p> </p>\n"
                        },
                        {
                            "type": "video",
                            "url": "https://youtu.be/cZjfzpQ3JUI",
                            "align": "left",
                            "caption": "Samengestelde zinnen: hoofd- en bijzinnen",
                            "poster": "https://img.youtube.com/vi/cZjfzpQ3JUI/maxresdefault.jpg"
                        }
                    ],
                    "sections": []
                },
                {
                    "reference": {
                        "value": "6522390"
                    },
                    "heading": {
                        "type": "heading",
                        "content": "Grammatica woordsoorten hoofdstuk 5",
                        "level": 2
                    },
                    "items": [
                        {
                            "type": "paragraph",
                            "content": "<p>Het onderwerp van woordsoorten hoofdstuk 5 is voegwoorden. Het lesdoel van deze les is:</p>\n<p>1. Aan het einde van deze les kun nevenschikkende en onderschikkende voegwoorden herkennen en gebruiken. </p>\n<p> </p>\n<p>In de kennisclip kun je uitleg vinden over nevenschikkende en onderschikkende voegwoorden. </p>\n<p> </p>\n"
                        },
                        {
                            "type": "video",
                            "url": "https://youtu.be/A32sEdKltOA",
                            "align": "left",
                            "caption": "Voegwoorden",
                            "poster": "https://img.youtube.com/vi/A32sEdKltOA/maxresdefault.jpg"
                        }
                    ],
                    "sections": []
                },
                {
                    "reference": {
                        "value": "6522397"
                    },
                    "heading": {
                        "type": "heading",
                        "content": "Grammatica zinsdelen hoofdstuk 6",
                        "level": 2
                    },
                    "items": [
                        {
                            "type": "paragraph",
                            "content": "<p>Het onderwerp van zinsdelen hoofdstuk 6 is zinsdeelzinnen. De lesdoelen van deze les zijn:</p>\n<p>1. Aan het einde van deze les kun je onderscheid maken tussen zinsdelen en zinsdeelzinnen.</p>\n<p>2. Aan het einde van deze les kun je zinsdeelzinnen herkennen en benoemen.</p>\n<p> </p>\n<p>In de kennisclip kun je uitleg vinden over zinsdeelzinnen.</p>\n<p> </p>\n"
                        },
                        {
                            "type": "video",
                            "url": "https://youtu.be/wVYmQzz63qM",
                            "align": "left",
                            "caption": "Zinsdeelzinnen",
                            "poster": "https://img.youtube.com/vi/wVYmQzz63qM/maxresdefault.jpg"
                        }
                    ],
                    "sections": []
                },
                {
                    "reference": {
                        "value": "6522400"
                    },
                    "heading": {
                        "type": "heading",
                        "content": "Grammatica woordsoorten hoofdstuk 6",
                        "level": 2
                    },
                    "items": [
                        {
                            "type": "paragraph",
                            "content": "<p>Het onderwerp van woordsoorten hoofdstuk 6 is het zelfstandig werkwoord, koppel- en hulpwerkwoord in samengestelde zinnen. Het lesdoel van deze les is:</p>\n<p>1. Aan het einde van deze les kun je zelfstandig werkwoorden, hulp- en koppelwerkwoorden in een zin herkennen.</p>\n<p> </p>\n<p>In de kennisclip kun je uitleg vinden over de werkwoorden in samengestelde zinnen.</p>\n<p> </p>\n"
                        },
                        {
                            "type": "video",
                            "url": "https://youtu.be/zFxJMiuvWS0",
                            "align": "left",
                            "caption": "Werkwoorden in samengestelde zinnen",
                            "poster": "https://img.youtube.com/vi/zFxJMiuvWS0/maxresdefault.jpg"
                        }
                    ],
                    "sections": []
                },
                {
                    "reference": {
                        "value": "6469696"
                    },
                    "heading": {
                        "type": "heading",
                        "content": "Grammatica extra materiaal",
                        "level": 2
                    },
                    "items": [
                        {
                            "type": "file",
                            "title": "Grammatica zinsdelen uitleg H1 t/m 3",
                            "file": "https://maken.wikiwijs.nl/userfiles/8/84312faee7c7ad9e128b67a6ef56d4096a0382fb.docx"
                        },
                        {
                            "type": "file",
                            "title": "Grammatica woordsoorten uitleg H1 t/m 3",
                            "file": "https://maken.wikiwijs.nl/userfiles/e/e941114ab76f35879f05c8f6b16984e94cf67b3a.docx"
                        },
                        {
                            "type": "file",
                            "title": "Oefentoets grammatica H1 t/m 3",
                            "file": "https://maken.wikiwijs.nl/userfiles/7/7b058fe3217be8fa97ac06975d64b4c7a983b7a9.docx"
                        },
                        {
                            "type": "file",
                            "title": "Antwoorden oefentoets grammatica H1 t/m 3",
                            "file": "https://maken.wikiwijs.nl/userfiles/e/ebea28f7f8e4b7e7f5ff56c96c5ab3c4f9c0ece3.docx"
                        },
                        {
                            "type": "file",
                            "title": "Oefentoets grammatica H1 t/m 6",
                            "file": "https://maken.wikiwijs.nl/userfiles/b/b6ffaedfc587cc9c5a655a99575f42e54ddf29a0.docx"
                        },
                        {
                            "type": "file",
                            "title": "Antwoorden oefentoets grammatica H1 t/m 6",
                            "file": "https://maken.wikiwijs.nl/userfiles/6/6ce539b89598ad238a2dc20ab0623069222b29ef.docx"
                        }
                    ],
                    "sections": []
                }
            ]
        },
        {
            "reference": {
                "value": "6752312"
            },
            "heading": {
                "type": "heading",
                "content": "Eindtoets",
                "level": 1
            },
            "items": [],
            "sections": [
                {
                    "reference": {
                        "value": "6752314"
                    },
                    "heading": {
                        "type": "heading",
                        "content": "Leesvaardigheid",
                        "level": 2
                    },
                    "items": [
                        {
                            "type": "paragraph",
                            "content": "<p>Zorg ervoor dat je alle onderdelen van leesvaardigheid beheerst. </p>\n<p> </p>\n<p>Hoofdstuk 1: hoofd- en bijzaken en kernzinnen bladzijde 12</p>\n<p>Hoofdstuk 2: tekstverbanden en signaalwoorden deel 1 bladzijde 42</p>\n<p>Hoofdstuk 3: tekstverbanden en signaalwoorden deel 2 bladzijde 72</p>\n<p>Hoofdstuk 4: feiten, meningen en argumenten bladzijde 102</p>\n<p>Hoofdstuk 5: kritisch lezen bladzijde 132</p>\n<p>Hoofdstuk 6: tekst en publiek bladzijde 162</p>\n"
                        }
                    ],
                    "sections": []
                },
                {
                    "reference": {
                        "value": "6752315"
                    },
                    "heading": {
                        "type": "heading",
                        "content": "Woordenschat",
                        "level": 2
                    },
                    "items": [
                        {
                            "type": "paragraph",
                            "content": "<p>Zorg ervoor dat je de woorden en uitdrukkingen van hoofdstuk 6 allemaal kent en kunt toepassen. Ik heb voor jullie een woordenlijst.</p>\n<p> </p>\n"
                        },
                        {
                            "type": "file",
                            "title": "Woordenlijst hoofdstuk 6",
                            "file": "https://maken.wikiwijs.nl/userfiles/a/a5502ec0df270ed469416b002e133b40d5e78695.docx"
                        }
                    ],
                    "sections": []
                },
                {
                    "reference": {
                        "value": "6752316"
                    },
                    "heading": {
                        "type": "heading",
                        "content": "Grammatica",
                        "level": 2
                    },
                    "items": [
                        {
                            "type": "paragraph",
                            "content": "<p>Zorg ervoor dat je alle onderdelen van grammatica beheerst.</p>\n<p> </p>\n<p><strong>Woordsoorten</strong></p>\n<p>Hoofdstuk 1: persoonlijk en bezittelijk voornaamwoord bladzijde 30</p>\n<p>Hoofdstuk 2: koppelwerkwoord en hulpwerkwoord bladzijde 60</p>\n<p>Hoofdstuk 3: werkwoorden bladzijde 90</p>\n<p>Hoofdstuk 4: telwoord bladzijde 120</p>\n<p>Hoofdstuk 5: voegwoord bladzijde 150</p>\n<p>Hoofdstuk 6: werkwoorden in samengestelde zinnen bladzijde 180</p>\n"
                        },
                        {
                            "type": "file",
                            "title": "Woordsoorten",
                            "file": "https://maken.wikiwijs.nl/userfiles/2/2047bd0ae16faae42f3f542cf24a47078ceb8def.docx"
                        },
                        {
                            "type": "paragraph",
                            "content": "<p> </p>\n<p><strong>Zinsdelen</strong></p>\n<p>Hoofdstuk 2: naamwoordelijk gezegde bladzijde 58</p>\n<p>Hoofdstuk 3: gezegde werkwoordelijk of naamwoordelijk bladzijde 88</p>\n<p>Hoofdstuk 4: bijvoeglijke bepaling bladzijde 118</p>\n<p>Hoofdstuk 5: samengestelde zinnen bladzijde 148</p>\n<p>Hoofdstuk 6: zinsdeelzinnen bladzijde 178</p>\n"
                        },
                        {
                            "type": "file",
                            "title": "Zinsdelen",
                            "file": "https://maken.wikiwijs.nl/userfiles/e/e24255fdb00ec53dcd352958bcb94a20c371f55c.docx"
                        }
                    ],
                    "sections": []
                },
                {
                    "reference": {
                        "value": "6752317"
                    },
                    "heading": {
                        "type": "heading",
                        "content": "Werkwoordspelling",
                        "level": 2
                    },
                    "items": [
                        {
                            "type": "paragraph",
                            "content": "<p>Zorg ervoor dat je alle onderdelen van werkwoordspelling beheerst.</p>\n<p> </p>\n<p><strong>Werkwoordspelling</strong></p>\n<p>Hoofdstuk 1: gebiedende wijs bladzijde 36</p>\n<p>Hoofdstuk 2: Engelse leenwoorden 66</p>\n<p>Hoofdstuk 3: lastige werkwoordsvormen -d of dt 96</p>\n<p>Hoofdstuk 4: meer lastige werkwoordsvormen 126</p>\n<p>Hoofdstuk 5: persoonsvorm in samengestelde zinnen 156</p>\n<p>Hoofdstuk 6: persoonsvorm tegenwoordige tijd of voltooid deelwoord bladzijde 186</p>\n"
                        },
                        {
                            "type": "file",
                            "title": "Werkwoordspelling",
                            "file": "https://maken.wikiwijs.nl/userfiles/9/9f7d83f4fa489431db3b97f00e1cd61eee840aed.docx"
                        }
                    ],
                    "sections": []
                }
            ]
        },
        {
            "reference": {
                "value": "6469535"
            },
            "heading": {
                "type": "heading",
                "content": "Fictie",
                "level": 1
            },
            "items": [],
            "sections": [
                {
                    "reference": {
                        "value": "6469597"
                    },
                    "heading": {
                        "type": "heading",
                        "content": "Fictie opdrachten",
                        "level": 2
                    },
                    "items": [
                        {
                            "type": "paragraph",
                            "content": "<p>Bij dit onderdeel kun je de opdrachten voor fictie vinden.</p>\n"
                        }
                    ],
                    "sections": []
                },
                {
                    "reference": {
                        "value": "6469599"
                    },
                    "heading": {
                        "type": "heading",
                        "content": "Fictie opdracht 1",
                        "level": 2
                    },
                    "items": [
                        {
                            "type": "file",
                            "title": "Fictie opdracht 1",
                            "file": "https://maken.wikiwijs.nl/userfiles/c/cca210f92f856072a37423462b3125069be416c6.docx"
                        }
                    ],
                    "sections": []
                },
                {
                    "reference": {
                        "value": "6469600"
                    },
                    "heading": {
                        "type": "heading",
                        "content": "Fictie opdracht 2",
                        "level": 2
                    },
                    "items": [
                        {
                            "type": "file",
                            "title": "Fictie opdracht 2",
                            "file": "https://maken.wikiwijs.nl/userfiles/9/9fcf7f13e59aa1c04900717a9c4e1c06483c93fc.docx"
                        }
                    ],
                    "sections": []
                },
                {
                    "reference": {
                        "value": "6687350"
                    },
                    "heading": {
                        "type": "heading",
                        "content": "Fictie opdracht 3",
                        "level": 2
                    },
                    "items": [
                        {
                            "type": "file",
                            "title": "Fictie opdracht 3",
                            "file": "https://maken.wikiwijs.nl/userfiles/5/5e460022b5b5a255ad39161de581db3aa1ec5162.docx"
                        }
                    ],
                    "sections": []
                }
            ]
        }
    ],
    "theme": {
        "banner": {
            "columns": [],
            "backgroundImageUrl": null,
            "dimension": null,
            "suppressTitle": null
        },
        "color": "#333333"
    },
    "tableOfContents": {
        "title": "Inhoudsopgave",
        "headings": [
            {
                "title": "Welkom",
                "reference": {
                    "value": "6469529"
                },
                "sections": []
            },
            {
                "title": "Hoe werkt deze site?",
                "reference": {
                    "value": "6469530"
                },
                "sections": []
            },
            {
                "title": "Woordenschat",
                "reference": {
                    "value": "6469533"
                },
                "sections": [
                    {
                        "title": "Woordenschat",
                        "reference": {
                            "value": "6469559"
                        },
                        "sections": []
                    },
                    {
                        "title": "Woordenschat hoofdstuk 1: vergelijking",
                        "reference": {
                            "value": "6469547"
                        },
                        "sections": []
                    },
                    {
                        "title": "Woordenschat hoofdstuk 2: metaforen en personificaties",
                        "reference": {
                            "value": "6469549"
                        },
                        "sections": []
                    },
                    {
                        "title": "Woordenschat hoofdstuk 3: voorzetsels en voorzetseluitdrukkingen",
                        "reference": {
                            "value": "6469550"
                        },
                        "sections": []
                    },
                    {
                        "title": "Woordenschat hoofdstuk 4: rijmende uitdrukkingen",
                        "reference": {
                            "value": "6612912"
                        },
                        "sections": []
                    },
                    {
                        "title": "Woordenschat hoofdstuk 5: uitdrukkingen uit handel en scheepvaart",
                        "reference": {
                            "value": "6612914"
                        },
                        "sections": []
                    },
                    {
                        "title": "Woordenschat hoofdstuk 6: oude naamvallen",
                        "reference": {
                            "value": "6612915"
                        },
                        "sections": []
                    },
                    {
                        "title": "Woordenschat extra materiaal ",
                        "reference": {
                            "value": "6469564"
                        },
                        "sections": []
                    }
                ]
            },
            {
                "title": "Leesvaardigheid",
                "reference": {
                    "value": "6469601"
                },
                "sections": [
                    {
                        "title": "Leesvaardigheid",
                        "reference": {
                            "value": "6469593"
                        },
                        "sections": []
                    },
                    {
                        "title": "Leesvaardigheid hoofdstuk 1",
                        "reference": {
                            "value": "6469570"
                        },
                        "sections": []
                    },
                    {
                        "title": "Leesvaardigheid hoofdstuk 2",
                        "reference": {
                            "value": "6469571"
                        },
                        "sections": []
                    },
                    {
                        "title": "Leesvaardigheid hoofdstuk 3",
                        "reference": {
                            "value": "6666748"
                        },
                        "sections": []
                    },
                    {
                        "title": "Leesvaardigheid hoofdstuk 4",
                        "reference": {
                            "value": "6666749"
                        },
                        "sections": []
                    },
                    {
                        "title": "Leesvaardigheid hoofdstuk 5",
                        "reference": {
                            "value": "6666750"
                        },
                        "sections": []
                    },
                    {
                        "title": "Leesvaardigheid hoofdstuk 6",
                        "reference": {
                            "value": "6666751"
                        },
                        "sections": []
                    },
                    {
                        "title": "Leesvaardigheid extra materiaal",
                        "reference": {
                            "value": "6469584"
                        },
                        "sections": []
                    }
                ]
            },
            {
                "title": "Grammatica",
                "reference": {
                    "value": "6469534"
                },
                "sections": [
                    {
                        "title": "Grammatica hoofdstuk 1 t/m 3",
                        "reference": {
                            "value": "6469604"
                        },
                        "sections": []
                    },
                    {
                        "title": "Grammatica herhaling zinsdelen havo 1",
                        "reference": {
                            "value": "6469662"
                        },
                        "sections": []
                    },
                    {
                        "title": "Grammatica herhaling woordsoorten havo 1",
                        "reference": {
                            "value": "6469663"
                        },
                        "sections": []
                    },
                    {
                        "title": "Grammatica zinsdelen hoofdstuk 1",
                        "reference": {
                            "value": "6469660"
                        },
                        "sections": []
                    },
                    {
                        "title": "Grammatica woordsoorten hoofdstuk 1",
                        "reference": {
                            "value": "6469661"
                        },
                        "sections": []
                    },
                    {
                        "title": "Grammatica zinsdelen hoofdstuk 2",
                        "reference": {
                            "value": "6469664"
                        },
                        "sections": []
                    },
                    {
                        "title": "Grammatica woordsoorten hoofdstuk 2",
                        "reference": {
                            "value": "6469666"
                        },
                        "sections": []
                    },
                    {
                        "title": "Grammatica zinsdelen hoofdstuk 3",
                        "reference": {
                            "value": "6469665"
                        },
                        "sections": []
                    },
                    {
                        "title": "Grammatica woordsoorten hoofdstuk 3",
                        "reference": {
                            "value": "6469667"
                        },
                        "sections": []
                    },
                    {
                        "title": "Grammatica zinsdelen hoofdstuk 4",
                        "reference": {
                            "value": "6522381"
                        },
                        "sections": []
                    },
                    {
                        "title": "Grammatica woordsoorten hoofdstuk 4",
                        "reference": {
                            "value": "6522382"
                        },
                        "sections": []
                    },
                    {
                        "title": "Grammatica zinsdelen hoofdstuk 5",
                        "reference": {
                            "value": "6522389"
                        },
                        "sections": []
                    },
                    {
                        "title": "Grammatica woordsoorten hoofdstuk 5",
                        "reference": {
                            "value": "6522390"
                        },
                        "sections": []
                    },
                    {
                        "title": "Grammatica zinsdelen hoofdstuk 6",
                        "reference": {
                            "value": "6522397"
                        },
                        "sections": []
                    },
                    {
                        "title": "Grammatica woordsoorten hoofdstuk 6",
                        "reference": {
                            "value": "6522400"
                        },
                        "sections": []
                    },
                    {
                        "title": "Grammatica extra materiaal",
                        "reference": {
                            "value": "6469696"
                        },
                        "sections": []
                    }
                ]
            },
            {
                "title": "Eindtoets",
                "reference": {
                    "value": "6752312"
                },
                "sections": [
                    {
                        "title": "Leesvaardigheid",
                        "reference": {
                            "value": "6752314"
                        },
                        "sections": []
                    },
                    {
                        "title": "Woordenschat",
                        "reference": {
                            "value": "6752315"
                        },
                        "sections": []
                    },
                    {
                        "title": "Grammatica",
                        "reference": {
                            "value": "6752316"
                        },
                        "sections": []
                    },
                    {
                        "title": "Werkwoordspelling",
                        "reference": {
                            "value": "6752317"
                        },
                        "sections": []
                    }
                ]
            },
            {
                "title": "Fictie",
                "reference": {
                    "value": "6469535"
                },
                "sections": [
                    {
                        "title": "Fictie opdrachten",
                        "reference": {
                            "value": "6469597"
                        },
                        "sections": []
                    },
                    {
                        "title": "Fictie opdracht 1",
                        "reference": {
                            "value": "6469599"
                        },
                        "sections": []
                    },
                    {
                        "title": "Fictie opdracht 2",
                        "reference": {
                            "value": "6469600"
                        },
                        "sections": []
                    },
                    {
                        "title": "Fictie opdracht 3",
                        "reference": {
                            "value": "6687350"
                        },
                        "sections": []
                    }
                ]
            },
            {
                "title": "Over dit lesmateriaal",
                "reference": {
                    "value": "colophon"
                },
                "sections": []
            }
        ]
    },
    "colophon": {
        "title": "Over dit lesmateriaal",
        "description": null,
        "imageSrc": null,
        "sources": [
            {
                "type": "video",
                "title": "Vergelijking",
                "origin": "Vergelijking",
                "customOrigin": null,
                "link": "https://youtu.be/A4Ugyx-v6dE",
                "visible": true
            },
            {
                "type": "video",
                "title": "Metaforen en personificaties",
                "origin": "Metaforen en personificaties",
                "customOrigin": null,
                "link": "https://youtu.be/j8Wfoj28bxc",
                "visible": true
            },
            {
                "type": "video",
                "title": "Voorzetsels en voorzetseluitdrukkingen",
                "origin": "Voorzetsels en voorzetseluitdrukkingen",
                "customOrigin": null,
                "link": "https://youtu.be/EwSQSyocsj8",
                "visible": true
            },
            {
                "type": "video",
                "title": "Rijmende uitdrukkingen",
                "origin": "Rijmende uitdrukkingen",
                "customOrigin": null,
                "link": "https://youtu.be/hKADF2esGQw",
                "visible": true
            },
            {
                "type": "video",
                "title": "Uitdrukkingen uit de tijd van handel en scheepvaart",
                "origin": "Uitdrukkingen uit de tijd van handel en scheepvaart",
                "customOrigin": null,
                "link": "https://youtu.be/t1NDW_sv4Ps",
                "visible": true
            },
            {
                "type": "video",
                "title": "Oude naamvallen",
                "origin": "Oude naamvallen",
                "customOrigin": null,
                "link": "https://youtu.be/PR2lU02_WqM",
                "visible": true
            },
            {
                "type": "video",
                "title": "Hoofdzaken, bijzaken en kernzinnen",
                "origin": "Hoofdzaken, bijzaken en kernzinnen",
                "customOrigin": null,
                "link": "https://youtu.be/6enczpP1Hao",
                "visible": true
            },
            {
                "type": "video",
                "title": "Tekstverbanden en signaalwoorden",
                "origin": "Tekstverbanden en signaalwoorden",
                "customOrigin": null,
                "link": "https://youtu.be/0nzddaUYIsc",
                "visible": true
            },
            {
                "type": "video",
                "title": "Tekstverbanden en signaalwoorden",
                "origin": "Tekstverbanden en signaalwoorden",
                "customOrigin": null,
                "link": "https://youtu.be/YD_tCMGAImk",
                "visible": true
            },
            {
                "type": "video",
                "title": "Feiten, meningen en argumenten",
                "origin": "Feiten, meningen en argumenten",
                "customOrigin": null,
                "link": "https://youtu.be/AEaSqcPuioA",
                "visible": true
            },
            {
                "type": "video",
                "title": "Kritisch lezen",
                "origin": "Kritisch lezen",
                "customOrigin": null,
                "link": "https://youtu.be/41DHQFGuMBk",
                "visible": true
            },
            {
                "type": "video",
                "title": "Tekst en publiek",
                "origin": "Tekst en publiek",
                "customOrigin": null,
                "link": "https://youtu.be/a_LlmlUO14o",
                "visible": true
            },
            {
                "type": "video",
                "title": "Zinsdelen en persoonsvorm",
                "origin": "Zinsdelen en persoonsvorm",
                "customOrigin": null,
                "link": "https://youtu.be/5V0vv2W5R00",
                "visible": true
            },
            {
                "type": "video",
                "title": "Onderwerp",
                "origin": "Onderwerp",
                "customOrigin": null,
                "link": "https://youtu.be/lk7yb-2Ytp4",
                "visible": true
            },
            {
                "type": "video",
                "title": "Werkwoordelijk gezegde",
                "origin": "Werkwoordelijk gezegde",
                "customOrigin": null,
                "link": "https://youtu.be/_nAw2K__DlU",
                "visible": true
            },
            {
                "type": "video",
                "title": "Lijdend en meewerkend voorwerp",
                "origin": "Lijdend en meewerkend voorwerp",
                "customOrigin": null,
                "link": "https://youtu.be/JVB1seykzw0",
                "visible": true
            },
            {
                "type": "video",
                "title": "Bijwoordelijke bepaling",
                "origin": "Bijwoordelijke bepaling",
                "customOrigin": null,
                "link": "https://youtu.be/c8Z2HHJVkk0",
                "visible": true
            },
            {
                "type": "video",
                "title": "Zelfstandig naamwoord",
                "origin": "Zelfstandig naamwoord",
                "customOrigin": null,
                "link": "https://youtu.be/fQ7jQzci1WM",
                "visible": true
            },
            {
                "type": "video",
                "title": "Bijvoeglijk naamwoord",
                "origin": "Bijvoeglijk naamwoord",
                "customOrigin": null,
                "link": "https://youtu.be/5b8HnHpXCPI",
                "visible": true
            },
            {
                "type": "video",
                "title": "Zelfstandig werkwoord en hulpwerkwoord",
                "origin": "Zelfstandig werkwoord en hulpwerkwoord",
                "customOrigin": null,
                "link": "https://youtu.be/5WMSBk-hnYg",
                "visible": true
            },
            {
                "type": "video",
                "title": "Aanwijzend en vragend voornaamwoord",
                "origin": "Aanwijzend en vragend voornaamwoord",
                "customOrigin": null,
                "link": "https://youtu.be/bGkQMSUm_1k",
                "visible": true
            },
            {
                "type": "video",
                "title": "Voorzetsel",
                "origin": "Voorzetsel",
                "customOrigin": null,
                "link": "https://youtu.be/Wgq52LyP6nY",
                "visible": true
            },
            {
                "type": "video",
                "title": "Bijwoord",
                "origin": "Bijwoord",
                "customOrigin": null,
                "link": "https://youtu.be/RnRfjjkuVnU",
                "visible": true
            },
            {
                "type": "video",
                "title": "Persoonlijk en bezittelijk voornaamwoord",
                "origin": "Persoonlijk en bezittelijk voornaamwoord",
                "customOrigin": null,
                "link": "https://youtu.be/e8LR6bcG9I8",
                "visible": true
            },
            {
                "type": "video",
                "title": "Naamwoordelijk gezegde",
                "origin": "Naamwoordelijk gezegde",
                "customOrigin": null,
                "link": "https://youtu.be/IJJy7LEWLmE",
                "visible": true
            },
            {
                "type": "video",
                "title": "Zelfstandig werkwoord, koppelwerkwoord en hulpwerkwoord",
                "origin": "Zelfstandig werkwoord, koppelwerkwoord en hulpwerkwoord",
                "customOrigin": null,
                "link": "https://youtu.be/TQXeW0eOsbA",
                "visible": true
            },
            {
                "type": "video",
                "title": "Naamwoordelijk gezegde",
                "origin": "Naamwoordelijk gezegde",
                "customOrigin": null,
                "link": "https://youtu.be/IJJy7LEWLmE",
                "visible": true
            },
            {
                "type": "video",
                "title": "Zelfstandig werkwoord, koppelwerkwoord en hulpwerkwoord",
                "origin": "Zelfstandig werkwoord, koppelwerkwoord en hulpwerkwoord",
                "customOrigin": null,
                "link": "https://youtu.be/TQXeW0eOsbA",
                "visible": true
            },
            {
                "type": "video",
                "title": "Bijvoeglijke bepaling",
                "origin": "Bijvoeglijke bepaling",
                "customOrigin": null,
                "link": "https://youtu.be/nPulrKvnuno",
                "visible": true
            },
            {
                "type": "video",
                "title": "Telwoorden",
                "origin": "Telwoorden",
                "customOrigin": null,
                "link": "https://youtu.be/4Ev6MDDouKg",
                "visible": true
            },
            {
                "type": "video",
                "title": "Samengestelde zinnen: hoofd- en bijzinnen",
                "origin": "Samengestelde zinnen: hoofd- en bijzinnen",
                "customOrigin": null,
                "link": "https://youtu.be/cZjfzpQ3JUI",
                "visible": true
            },
            {
                "type": "video",
                "title": "Voegwoorden",
                "origin": "Voegwoorden",
                "customOrigin": null,
                "link": "https://youtu.be/A32sEdKltOA",
                "visible": true
            },
            {
                "type": "video",
                "title": "Zinsdeelzinnen",
                "origin": "Zinsdeelzinnen",
                "customOrigin": null,
                "link": "https://youtu.be/wVYmQzz63qM",
                "visible": true
            },
            {
                "type": "video",
                "title": "Werkwoorden in samengestelde zinnen",
                "origin": "Werkwoorden in samengestelde zinnen",
                "customOrigin": null,
                "link": "https://youtu.be/zFxJMiuvWS0",
                "visible": true
            }
        ],
        "metadata": [
            {
                "key": "intendedEndUserRole",
                "label": "Eindgebruiker",
                "terms": [
                    "leerling/student"
                ]
            },
            {
                "key": "learningTime",
                "label": "Studiebelasting",
                "terms": [
                    "4 uur en 0 minuten"
                ]
            }
        ],
        "usedLearningResources": []
    }
}